{"name":"Frenkie de Jong"}
{"name":"Antoine Griezmann"}
{"name":"Memphis Depay"}
{"name":"Rúben Dias"}
{"name":"Ricardo Rodríguez"}
{"name":"Jordan Pickford"}
{"name":"Matthijs de Ligt"}
{"name":"Sergio Ramos"}
{"name":"Yann Sommer"}
{"name":"Georginio Wijnaldum"}
{"name":"Jasper Cillessen"}
{"name":"Granit Xhaka"}
{"name":"Rui Patrício"}
{"name":"Nico Elvedi"}
{"name":"Harry Maguire"}
{"name":"Bernardo Silva"}
{"name":"Gianluigi Donnarumma"}
{"name":"Virgil van Dijk"}
{"name":"Ibrahim Šehić"}
{"name":"Romelu Lukaku"}
{"name":"Toby Alderweireld"}
{"name":"Toni Kroos"}
{"name":"Aleksandar Mitrović"}
{"name":"Hugo Lloris"}
{"name":"Cristiano Ronaldo"}
{"name":"Leonardo Bonucci"}
{"name":"Raheem Sterling"}
{"name":"Manuel Akanji"}
{"name":"Christian Eriksen"}
{"name":"Joshua Kimmich"}
{"name":"Serge Gnabry"}
{"name":"Kamil Glik"}
{"name":"Matthias Ginter"}
{"name":"Daley Blind"}
{"name":"Harry Kane"}
{"name":"Manuel Neuer"}
{"name":"Mykola Matviyenko"}
{"name":"Dries Mertens"}
{"name":"Jorginho"}
{"name":"Lukas Hradecky"}
{"name":"Raphaël Guerreiro"}
{"name":"Kasper Schmeichel"}
{"name":"Teemu Pukki"}
{"name":"Dejan Lovren"}
{"name":"Andriy Pyatov"}
{"name":"Eran Zahavi"}
{"name":"Jan Bednarek"}
{"name":"Paulus Arajuuri"}
{"name":"Fabian Schär"}
{"name":"Aleksandar Dragović"}
{"name":"Kevin De Bruyne"}
{"name":"Milan Škriniar"}
{"name":"Marco Verratti"}
{"name":"Pepe"}
{"name":"Anthony Moris"}
{"name":"Willi Orbán"}
{"name":"Simon Kjær"}
{"name":"Raphaël Varane"}
{"name":"Luka Modrić"}
{"name":"Bibras Natcho"}
{"name":"Kylian Mbappé"}
{"name":"Youri Tielemans"}
{"name":"John McGinn"}
{"name":"Shane Duffy"}
{"name":"Dušan Tadić"}
{"name":"Niklas Süle"}
{"name":"Benjamin Pavard"}
{"name":"Domagoj Vida"}
{"name":"Kyle Walker"}
{"name":"Kári Árnason"}
{"name":"Andreas  Christensen"}
{"name":"Kaan Ayhan"}
{"name":"Rune Jarstein"}
{"name":"Declan Rice"}
{"name":"Nikola Milenković"}
{"name":"Miralem Pjanić"}
{"name":"Marcus Rashford"}
{"name":"Martin Hinteregger"}
{"name":"Jan Oblak"}
{"name":"Robin Olsen"}
{"name":"Merih Demiral"}
{"name":"Jason Denayer"}
{"name":"Grzegorz Krychowiak"}
{"name":"Giorgio Chiellini"}
{"name":"Marten de Roon"}
{"name":"Thibaut Courtois"}
{"name":"Hakan Çalhanoğlu"}
{"name":"Birkir Bjarnason"}
{"name":"Josep Gomes"}
{"name":"Mateo Kovačić"}
{"name":"Pierre-Emile Højbjerg"}
{"name":"Dominik Livaković"}
{"name":"Sergio Busquets"}
{"name":"Thorgan Hazard"}
{"name":"Mathias Jørgensen"}
{"name":"Glen Kamara"}
{"name":"Konstantinos Laifis"}
{"name":"Georgi Dzhikiya"}
{"name":"Tigran Barseghyan"}
{"name":"İlkay Gündoğan"}
{"name":"Ioannis Kousoulos"}
{"name":"Eden Hazard"}
{"name":"Miha Mevlja"}
{"name":"Victor Lindelöf"}
{"name":"Guram Kashia"}
{"name":"Berat Djimsiti"}
{"name":"Bartosz Bereszyński"}
{"name":"João Cancelo"}
{"name":"Oleksandr Zinchenko"}
{"name":"Remo Freuler"}
{"name":"Sergei Maliy"}
{"name":"Nemanja Maksimović"}
{"name":"Ciprian Tătăruşanu"}
{"name":"Antonio Rüdiger"}
{"name":"Ragnar Sigurdsson"}
{"name":"Mikael Lustig"}
{"name":"John Stones"}
{"name":"Thomas Delaney"}
{"name":"Olivier Giroud"}
{"name":"N'Golo Kanté"}
{"name":"Axel Witsel"}
{"name":"Denis Zakaria"}
{"name":"Ben Chilwell"}
{"name":"Mert Günok"}
{"name":"Fidan Aliti"}
{"name":"Nicolò Barella"}
{"name":"Aleksandr Martynovich"}
{"name":"Ruslan Malinovskyi"}
{"name":"Joona Toivio"}
{"name":"Oleksandr Karavaev"}
{"name":"Quincy Promes"}
{"name":"Martin Dúbravka"}
{"name":"Darren Randolph"}
{"name":"José Gayà"}
{"name":"Haris Seferović"}
{"name":"Jonny Evans"}
{"name":"Craig Cathcart"}
{"name":"Wayne Hennessey"}
{"name":"Péter Gulácsi"}
{"name":"Kristoffer Olsson"}
{"name":"Giorgi Loria"}
{"name":"David de Gea"}
{"name":"Jaba Kankava"}
{"name":"Jan Vertonghen"}
{"name":"Stefan Lainer"}
{"name":"Denzel Dumfries"}
{"name":"Marc Vales"}
{"name":"Timo Werner"}
{"name":"Ivan Perišić"}
{"name":"Eli Dasa"}
{"name":"Vasil Bozhikov"}
{"name":"Tomáš Souček"}
{"name":"Thomas Meunier"}
{"name":"Steve Borg"}
{"name":"Andy Robertson"}
{"name":"Benjamin Büchel"}
{"name":"Xherdan Shaqiri"}
{"name":"Sverrir Ingason"}
{"name":"Juraj Kucka"}
{"name":"Magomed Ozdoev"}
{"name":"Eric Dier"}
{"name":"Ryan Christie"}
{"name":"Kieran Trippier"}
{"name":"Michy Batshuayi"}
{"name":"Marek Hamšík"}
{"name":"Joseph Mbong"}
{"name":"Gylfi Sigurdsson"}
{"name":"Josip Iličić"}
{"name":"David Marshall"}
{"name":"Roy Chipolina"}
{"name":"Alexei Koşelev"}
{"name":"Vitaliy Mykolenko"}
{"name":"Igor Armaş"}
{"name":"Mário Fernandes"}
{"name":"Henry Bonello"}
{"name":"Çağlar Söyüncü"}
{"name":"Bruno Fernandes"}
{"name":"Paddy McNair"}
{"name":"William Carvalho"}
{"name":"Okay Yokuşlu"}
{"name":"Presnel Kimpembe"}
{"name":"Kamil Grosicki"}
{"name":"Robert Lewandowski"}
{"name":"Egzijan Alioski"}
{"name":"Brandur Hendriksson"}
{"name":"Ondřej Čelůstka"}
{"name":"Siniša Saničanin"}
{"name":"Viktor Tsygankov"}
{"name":"Kristoffer Ajer"}
{"name":"Sergei Lepmets"}
{"name":"Edvinas Girdvainis"}
{"name":"Elia Benedettini"}
{"name":"Fedor Kudryashov"}
{"name":"Piotr Zieliński"}
{"name":"Connor Roberts"}
{"name":"Gareth Bale"}
{"name":"Varazdat Haroyan"}
{"name":"Eytan Tibi"}
{"name":"Hovhannes Hambartsumyan"}
{"name":"Daler Kuzyaev"}
{"name":"Danilo"}
{"name":"Badavi Hüseynov"}
{"name":"Bailey Peacock-Farrell"}
{"name":"Marcelo Brozović"}
{"name":"Nikola Vlašić"}
{"name":"Strahil Popov"}
{"name":"Leon Goretzka"}
{"name":"Enis Bardi"}
{"name":"Roman Yaremchuk"}
{"name":"Ádám Szalai"}
{"name":"Ardian Ismajli"}
{"name":"Ben Davies"}
{"name":"Kostas Fortounis"}
{"name":"José Fonte"}
{"name":"Maxime Chanot"}
{"name":"Tomasz Kędziora"}
{"name":"Joe Gomez"}
{"name":"Dani Carvajal"}
{"name":"Georgiy Bushchan"}
{"name":"Harry Wilson"}
{"name":"Sebastian Larsson"}
{"name":"Stuart Dallas"}
{"name":"Ethan Ampadu"}
{"name":"Nicholas Ioannou"}
{"name":"Kevin Mbabu"}
{"name":"Hannes Halldórsson"}
{"name":"Stefan Ilsanker"}
{"name":"Stefan Ristovski"}
{"name":"Thiago Alcántara"}
{"name":"Ross Barkley"}
{"name":"Artem Dzyuba"}
{"name":"Pāvels Šteinbors"}
{"name":"Wojciech Szczęsny"}
{"name":"Pau Torres"}
{"name":"Amir Rrahmani"}
{"name":"Saúl Ñíguez"}
{"name":"Tomáš Vaclík"}
{"name":"Viljormur Davidsen"}
{"name":"Łukasz Fabiański"}
{"name":"Lucas Hernández"}
{"name":"Tin Jedvaj"}
{"name":"Nicusor Bancu"}
{"name":"Atli Gregersen"}
{"name":"Daniel Wass"}
{"name":"Omar Elabdellaoui"}
{"name":"Igor Stasevich"}
{"name":"Laurent Jans"}
{"name":"Denis Cheryshev"}
{"name":"Leroy Sané"}
{"name":"Darko Velkoski"}
{"name":"Bahlul Mustafazade"}
{"name":"Ernestas Šetkus"}
{"name":"Dor Peretz"}
{"name":"Sheran Yeini"}
{"name":"Petar Stojanović"}
{"name":"Oleg Reabciuk"}
{"name":"Stole Dimitrievski"}
{"name":"Borna Barišić"}
{"name":"Ari Skúlason"}
{"name":"Alessandro Florenzi"}
{"name":"Kyle Goldwin"}
{"name":"Nikita Naumov"}
{"name":"Serhiy Kryvtsov"}
{"name":"Kai Havertz"}
{"name":"Vedat Muriqi"}
{"name":"Eljif Elmas"}
{"name":"Arijanet Muric"}
{"name":"Ádám Nagy"}
{"name":"Hallur Hansson"}
{"name":"Frédéric Veseli"}
{"name":"Victor Pálsson"}
{"name":"Gonçalo Guedes"}
{"name":"Besar Halimi"}
{"name":"Josip Brekalo"}
{"name":"Francesco Acerbi"}
{"name":"Marcus Berg"}
{"name":"Vincent Kompany"}
{"name":"Ryan Babel"}
{"name":"Valon Berisha"}
{"name":"Predrag Rajković"}
{"name":"Daniel Kaufmann"}
{"name":"Rodri"}
{"name":"Patrik Schick"}
{"name":"Fabián Ruiz"}
{"name":"Edimilson Fernandes"}
{"name":"Denis Polyakov"}
{"name":"Mergim Vojvoda"}
{"name":"Scott McTominay"}
{"name":"Lars Gerson"}
{"name":"Andrei Agius"}
{"name":"Joseph Chipolina"}
{"name":"Stanislav Lobotka"}
{"name":"Ozan Tufan"}
{"name":"Daniel James"}
{"name":"Zach Muscat"}
{"name":"Pontus Jansson"}
{"name":"Alexander Sørloth"}
{"name":"Julian Baumgartlinger"}
{"name":"Gara Garayev"}
{"name":"Ferran Torres"}
{"name":"Ofir Marciano"}
{"name":"Valentino Lazaro"}
{"name":"Tomas Švedkauskas"}
{"name":"Domantas Šimkus"}
{"name":"Zeki Çelik"}
{"name":"Henrik Dalsgaard"}
{"name":"Haitam Aleesami"}
{"name":"Emil Balayev"}
{"name":"Heini Vatnsdal"}
{"name":"Lucas Digne"}
{"name":"Jakub Jankto"}
{"name":"Max Llovera"}
{"name":"Alin Toşca"}
{"name":"Martin Ødegaard"}
{"name":"Gergő Lovrencsics"}
{"name":"Lukas Klostermann"}
{"name":"Moisés San Nicolás"}
{"name":"Albert Rusnák"}
{"name":"Mikel Oyarzabal"}
{"name":"Andreas Granqvist"}
{"name":"Cengiz Ünder"}
{"name":"Andrei Semenov"}
{"name":"Róbert Mak"}
{"name":"Nico Schulz"}
{"name":"Arijan Ademi"}
{"name":"Tasos Bakasetas"}
{"name":"Davide Simoncini"}
{"name":"Peter Pekarík"}
{"name":"Otar Kakabadze"}
{"name":"Marko Simić"}
{"name":"Shakhrudin Magomedaliyev"}
{"name":"Karol Mets"}
{"name":"Hördur Magnússon"}
{"name":"Ádám Lang"}
{"name":"Roberts Savaļnieks"}
{"name":"Sead Kolašinac"}
{"name":"Clément Lenglet"}
{"name":"Mārcis Ošs"}
{"name":"Ole Selnæs"}
{"name":"Temirlan Yerlanov"}
{"name":"Carlos Zeca"}
{"name":"Phil Foden"}
{"name":"Rasmus Schüller"}
{"name":"Mahmut Tekdemir"}
{"name":"Viktor Claesson"}
{"name":"David Alaba"}
{"name":"Dirk Carlson"}
{"name":"Denis Vavro"}
{"name":"Guilherme"}
{"name":"Dimitris Kourbelis"}
{"name":"Robert Skov"}
{"name":"Leandro Barreiro"}
{"name":"Toni Šunjić"}
{"name":"Anton Nedyalkov"}
{"name":"Nélson Semedo"}
{"name":"Kaspars Dubra"}
{"name":"Odmar Faerø"}
{"name":"Robin Lod"}
{"name":"Răzvan Marin"}
{"name":"Kamo Hovhannisyan"}
{"name":"Nicolae Stanciu"}
{"name":"Ramil Sheydaev"}
{"name":"Taras Stepanenko"}
{"name":"Vladimír Coufal"}
{"name":"Aram Airapetyan"}
{"name":"Martin Braithwaite"}
{"name":"Charlie Mulgrew"}
{"name":"Munas Dabbur"}
{"name":"Mario Gavranović"}
{"name":"Edin Džeko"}
{"name":"Jere Uronen"}
{"name":"Dominik Szoboszlai"}
{"name":"Chris Mepham"}
{"name":"Dedryck Boyata"}
{"name":"Ryan Fraser"}
{"name":"Georgi Kostadinov"}
{"name":"Marco Asensio"}
{"name":"Paul Pogba"}
{"name":"Vladimír Darida"}
{"name":"Rúben Neves"}
{"name":"Kire Ristevski"}
{"name":"Jesús Navas"}
{"name":"Joe Allen"}
{"name":"Saulius Mikoliūnas"}
{"name":"Diogo Jota"}
{"name":"Cristiano Biraghi"}
{"name":"Aljaž Struna"}
{"name":"Pierre Bengtsson"}
{"name":"Illia Zabarnyi"}
{"name":"Callum McGregor"}
{"name":"Adem Ljajić"}
{"name":"Ermin Bičakčić"}
{"name":"Bruno Petković"}
{"name":"Manuel Locatelli"}
{"name":"Yevhen Konoplyanka"}
{"name":"Mats Hummels"}
{"name":"Visar Musliu"}
{"name":"Manuel Battistini"}
{"name":"Jakub Brabec"}
{"name":"Maksim Medvedev"}
{"name":"Stefan Mitrović"}
{"name":"Kenny McLean"}
{"name":"Vlad Chiricheş"}
{"name":"Samuel Umtiti"}
{"name":"Jakub Moder"}
{"name":"Steven Davis"}
{"name":"Krzysztof Piątek"}
{"name":"Andriy Yarmolenko"}
{"name":"Sokratis Papastathopoulos"}
{"name":"Ludwig Augustinsson"}
{"name":"Kostakis Artymatas"}
{"name":"Emerson"}
{"name":"Kristian Dimitrov"}
{"name":"Aleksandr Golovin"}
{"name":"Lorenzo Insigne"}
{"name":"Andrea Belotti"}
{"name":"Ciro Immobile"}
{"name":"Filip Mladenović"}
{"name":"Artak Grigoryan"}
{"name":"Isco"}
{"name":"Michalis Bakakis"}
{"name":"Max Göppel"}
{"name":"Kamil Jóźwiak"}
{"name":"Zsolt Kalmár"}
{"name":"Fabian Delph"}
{"name":"Tim Sparv"}
{"name":"Stephen O'Donnell"}
{"name":"Enda Stevens"}
{"name":"Ildefons Lima"}
{"name":"Duje Ćaleta-Car"}
{"name":"Jacek Góralski"}
{"name":"Chambos Kyriakou"}
{"name":"John Sergeant"}
{"name":"Bauyrzhan Islamkhan"}
{"name":"Rade Krunić"}
{"name":"Aleksandar Kolarov"}
{"name":"Veaceslav Posmac"}
{"name":"Birkir Saevarsson"}
{"name":"Marko Vešović"}
{"name":"Jesse Joronen"}
{"name":"Elseid Hysaj"}
{"name":"Jan Bořil"}
{"name":"Adrien Rabiot"}
{"name":"Boban Nikolov"}
{"name":"Jure Balkovec"}
{"name":"Kenan Karaman"}
{"name":"Marc Rebés"}
{"name":"Arvydas Novikovas"}
{"name":"Henrikh Mkhitaryan"}
{"name":"Michael Smith"}
{"name":"Nir Bitton"}
{"name":"Håvard Nordtveit"}
{"name":"Andreas Ulmer"}
{"name":"Ibrahim Dresevic"}
{"name":"Joël Veltman"}
{"name":"Attila Fiola"}
{"name":"Umut Meraş"}
{"name":"Stefan Posch"}
{"name":"Dávid Hancko"}
{"name":"Ervin Zukanovic"}
{"name":"Gerson Rodrigues"}
{"name":"Nika Kvekveskiri"}
{"name":"Joonas Tamm"}
{"name":"Alexandr Marochkin"}
{"name":"Mason Mount"}
{"name":"Antonijs Černomordijs"}
{"name":"Keidi Bare"}
{"name":"Artur Pikk"}
{"name":"Andreas Malin"}
{"name":"David Pavelka"}
{"name":"Jamal Lewis"}
{"name":"Breel Embolo"}
{"name":"Benjamin Kololli"}
{"name":"Emil Forsberg"}
{"name":"Robin Quaison"}
{"name":"Ivan Maevski"}
{"name":"Hatem Elhamed"}
{"name":"Gerard Moreno"}
{"name":"Marlos"}
{"name":"Corentin Tolisso"}
{"name":"Cătălin Carp"}
{"name":"Scott McKenna"}
{"name":"Manor Solomon"}
{"name":"Arkadiusz Milik"}
{"name":"Dayle Coleing"}
{"name":"Vincent Thill"}
{"name":"James McClean"}
{"name":"Darko Todorović"}
{"name":"Tamás Kádár"}
{"name":"Luka Jović"}
{"name":"Marcus Danielson"}
{"name":"Samir Ujkani"}
{"name":"João Félix"}
{"name":"Fredrik Jensen"}
{"name":"Loai Taha"}
{"name":"Jasmin Kurtić"}
{"name":"Marko Dmitrović"}
{"name":"Nikita Baranov"}
{"name":"George Puşcaş"}
{"name":"Eldar Ćivić"}]